{
  "ספריות-קודש-פרדי-2026": {
    "1": [
      "אביאל",
      "דגם אביאל",
      "ספריה אביאל",
      "ספריית אביאל",
      "פרדי ספריות קודש"
    ],
    "2": [
      "אביהו",
      "דגם אביהו",
      "ספריה אביהו",
      "ספריית אביהו",
      "פרדי ספריות קודש"
    ],
    "3": [
      "אבינדב",
      "דגם אבינדב",
      "ספריה אבינדב",
      "ספריית אבינדב",
      "פרדי ספריות קודש"
    ],
    "4": [
      "אביתר",
      "דגם אביתר",
      "ספריה אביתר",
      "ספריית אביתר",
      "פרדי ספריות קודש"
    ],
    "5": [
      "אהרן",
      "דגם אהרן",
      "ספריה אהרן",
      "ספריית אהרן",
      "אהרון",
      "דגם אהרון",
      "ספריה אהרון",
      "ספריית אהרון",
      "פרדי ספריות קודש"
    ],
    "6": [
      "אופק",
      "דגם אופק",
      "ספריה אופק",
      "ספריית אופק",
      "פרדי ספריות קודש"
    ],
    "7": [
      "אוריה",
      "דגם אוריה",
      "ספריה אוריה",
      "ספריית אוריה",
      "פרדי ספריות קודש"
    ],
    "8": [
      "אייל",
      "דגם אייל",
      "ספריה אייל",
      "ספריית אייל",
      "פרדי ספריות קודש"
    ],
    "9": [
      "איתמר",
      "דגם איתמר",
      "ספריה איתמר",
      "ספריית איתמר",
      "פרדי ספריות קודש"
    ],
    "10": [
      "אלול",
      "דגם אלול",
      "ספריה אלול",
      "ספריית אלול",
      "פרדי ספריות קודש"
    ],
    "11": [
      "אליה",
      "דגם אליה",
      "ספריה אליה",
      "ספריית אליה",
      "פרדי ספריות קודש"
    ],
    "12": [
      "אלמוג",
      "דגם אלמוג",
      "ספריה אלמוג",
      "ספריית אלמוג",
      "פרדי ספריות קודש"
    ],
    "13": [
      "אליעזר",
      "דגם אליעזר",
      "ספריה אליעזר",
      "ספריית אליעזר",
      "פרדי ספריות קודש"
    ],
    "14": [
      "אלקנה",
      "דגם אלקנה",
      "ספריה אלקנה",
      "ספריית אלקנה",
      "פרדי ספריות קודש"
    ],
    "15": [
      "אלרואי",
      "דגם אלרואי",
      "ספריה אלרואי",
      "ספריית אלרואי",
      "אל רואי",
      "דגם אל רואי",
      "ספריה אל רואי",
      "ספריית אל רואי",
      "פרדי ספריות קודש"
    ],
    "16": [
      "אריאל",
      "דגם אריאל",
      "ספריה אריאל",
      "ספריית אריאל",
      "פרדי ספריות קודש"
    ],
    "17": [
      "ארד",
      "דגם ארד",
      "ספריה ארד",
      "ספריית ארד",
      "פרדי ספריות קודש"
    ],
    "18": [
      "ארז",
      "דגם ארז",
      "ספריה ארז",
      "ספריית ארז",
      "פרדי ספריות קודש"
    ],
    "19": [
      "ארי",
      "דגם ארי",
      "ספריה ארי",
      "ספריית ארי",
      "פרדי ספריות קודש"
    ],
    "20": [
      "אשר",
      "דגם אשר",
      "ספריה אשר",
      "ספריית אשר",
      "פרדי ספריות קודש"
    ],
    "21": [
      "בנימין",
      "דגם בנימין",
      "ספריה בנימין",
      "ספריית בנימין",
      "בינימין",
      "דגם בינימין",
      "ספריה בינימין",
      "ספריית בינימין",
      "בןימין",
      "דגם בןימין",
      "ספריה בןימין",
      "ספריית בןימין",
      "פרדי ספריות קודש"
    ],
    "22": [
      "בן ציון",
      "דגם בן ציון",
      "ספריה בן ציון",
      "ספריית בן ציון",
      "בנציונ",
      "דגם בנציונ",
      "ספריה בנציונ",
      "ספריית בנציונ",
      "בנציוני",
      "דגם בנציוני",
      "ספריה בנציוני",
      "ספריית בנציוני",
      "בנציון",
      "דגם בנציון",
      "ספריה בנציון",
      "ספריית בנציון",
      "פרדי ספריות קודש"
    ],
    "23": [
      "בראל",
      "דגם בראל",
      "ספריה בראל",
      "ספריית בראל",
      "פרדי ספריות קודש"
    ],
    "24": [
      "גלעד",
      "דגם גלעד",
      "ספריה גלעד",
      "ספריית גלעד",
      "פרדי ספריות קודש"
    ],
    "25": [
      "זבולון",
      "דגם זבולון",
      "ספריה זבולון",
      "ספריית זבולון",
      "זבולן",
      "דגם זבולן",
      "ספריה זבולן",
      "ספריית זבולן",
      "פרדי ספריות קודש"
    ],
    "26": [
      "חיים",
      "דגם חיים",
      "ספריה חיים",
      "ספריית חיים",
      "פרדי ספריות קודש"
    ],
    "27": [
      "חנניה",
      "דגם חנניה",
      "ספריה חנניה",
      "ספריית חנניה",
      "פרדי ספריות קודש"
    ],
    "28": [
      "יהודה",
      "דגם יהודה",
      "ספריה יהודה",
      "ספריית יהודה",
      "פרדי ספריות קודש"
    ],
    "29": [
      "יואל",
      "דגם יואל",
      "ספריה יואל",
      "ספריית יואל",
      "פרדי ספריות קודש"
    ],
    "30": [
      "יונה",
      "דגם יונה",
      "ספריה יונה",
      "ספריית יונה",
      "פרדי ספריות קודש"
    ],
    "31": [
      "יונתן",
      "דגם יונתן",
      "ספריה יונתן",
      "ספריית יונתן",
      "יהונתן",
      "דגם יהונתן",
      "ספריה יהונתן",
      "ספריית יהונתן",
      "פרדי ספריות קודש"
    ],
    "32": [
      "יוסף",
      "דגם יוסף",
      "ספריה יוסף",
      "ספריית יוסף",
      "פרדי ספריות קודש"
    ],
    "33": [
      "יחזקאל",
      "דגם יחזקאל",
      "ספריה יחזקאל",
      "ספריית יחזקאל",
      "פרדי ספריות קודש"
    ],
    "34": [
      "ינאי",
      "דגם ינאי",
      "ספריה ינאי",
      "ספריית ינאי",
      "פרדי ספריות קודש"
    ],
    "35": [
      "יעקב",
      "דגם יעקב",
      "ספריה יעקב",
      "ספריית יעקב",
      "פרדי ספריות קודש"
    ],
    "36": [
      "נחמן",
      "דגם נחמן",
      "ספריה נחמן",
      "ספריית נחמן",
      "פרדי ספריות קודש"
    ],
    "37": [
      "ניתאי",
      "דגם ניתאי",
      "ספריה ניתאי",
      "ספריית ניתאי",
      "נתאי",
      "דגם נתאי",
      "ספריה נתאי",
      "ספריית נתאי",
      "פרדי ספריות קודש"
    ],
    "38": [
      "נפתלי",
      "דגם נפתלי",
      "ספריה נפתלי",
      "ספריית נפתלי",
      "פרדי ספריות קודש"
    ],
    "39": [
      "נתן",
      "דגם נתן",
      "ספריה נתן",
      "ספריית נתן",
      "פרדי ספריות קודש"
    ],
    "40": [
      "נתנאל",
      "דגם נתנאל",
      "ספריה נתנאל",
      "ספריית נתנאל",
      "פרדי ספריות קודש"
    ],
    "41": [
      "עברי",
      "דגם עברי",
      "ספריה עברי",
      "ספריית עברי",
      "פרדי ספריות קודש"
    ],
    "42": [
      "עומרי",
      "דגם עומרי",
      "ספריה עומרי",
      "ספריית עומרי",
      "פרדי ספריות קודש"
    ]
  },
  "היי-ריזר-קואליטה-2026": {
    "1": [
      "קואליטה",
      "מיטות קואליטה",
      "qualita",
      "Qualita"
    ],
    "3": [
      "חמניה",
      "חמנייה",
      "החמניה",
      "דגם חמניה",
      "מיטת חמניה",
      "Sunflower",
      "sun flower"
    ],
    "4": [
      "לבנדר עם ארגז",
      "לבנדר",
      "דגם לבנדר",
      "מיטת לבנדר",
      "Lavender",
      "לבנדר ארגז"
    ],
    "5": [
      "לבנדר ללא ארגז",
      "לבנדר",
      "דגם לבנדר",
      "מיטת לבנדר",
      "Lavender",
      "ללא ארגז"
    ],
    "6": [
      "כלנית",
      "הכלנית",
      "דגם כלנית",
      "מיטת כלנית",
      "Anemon",
      "Anemone",
      "Anemone bed"
    ],
    "7": [
      "לילך",
      "דגם לילך",
      "מיטת לילך",
      "Lilac"
    ],
    "8": [
      "קאלה",
      "קלה",
      "דגם קאלה",
      "מיטת קאלה",
      "Calla"
    ],
    "9": [
      "נרקיס",
      "הנרקיס",
      "דגם נרקיס",
      "מיטת נרקיס",
      "Narcissus",
      "Narcis"
    ],
    "10": [
      "ורד",
      "דגם ורד",
      "מיטת ורד",
      "Rose"
    ],
    "11": [
      "שושן",
      "דגם שושן",
      "מיטת שושן",
      "Lily",
      "לילי"
    ],
    "12": [
      "טוליפ",
      "דגם טוליפ",
      "מיטת טוליפ",
      "Tulip"
    ],
    "13": [
      "כלנית קומותיים",
      "קומותיים כלנית",
      "דגם כלנית קומותיים",
      "מיטת קומותיים כלנית",
      "Anemon קומותיים",
      "Anemone bunk",
      "מיטת קומותיים"
    ],
    "14": [
      "סחלב קומותיים",
      "קומותיים סחלב",
      "דגם סחלב",
      "מיטת קומותיים סחלב",
      "Orchid",
      "אורכיד",
      "אורכידאה",
      "מיטת קומותיים"
    ],
    "15": [
      "שושן קומותיים",
      "קומותיים שושן",
      "דגם שושן קומותיים",
      "מיטת קומותיים שושן",
      "Lily קומותיים",
      "Lily bunk",
      "מיטת קומותיים"
    ],
    "16": [
      "מזרן נוער",
      "מזרני בייפלקס",
      "בייפלקס",
      "מזרן דרימלייק",
      "דרימלייק",
      "מזרן מורבידו",
      "מורבידו",
      "קואליטיום",
      "Qualitium",
      "Dreamlike",
      "Morbido",
      "Biflex"
    ],
    "17": [
      "מחירון מיטות",
      "מחירון מזרנים",
      "מחירון תוספות",
      "חמניה",
      "כלנית",
      "נרקיס",
      "שושן",
      "ורד",
      "קאלה",
      "לבנדר",
      "טוליפ",
      "לילך",
      "קומותיים כלנית",
      "קומותיים שושן",
      "קומותיים סחלב",
      "מחירון קואליטה"
    ],
    "18": [
      "מידות מזרנים",
      "מחירון הובלות",
      "כפולה 80",
      "כפולה 90",
      "כפולה עם ארגז עליון",
      "משולשת",
      "מרובעת",
      "גובה מיטה",
      "רוחב מזרן",
      "אורך מזרן"
    ],
    "19": [
      "קואליטה",
      "מיטות קואליטה",
      "qualita"
    ]
  },
  "מיטות-נגר-בירץ'-2026": {
    "2": [
      "נוגה כפולה",
      "דגם נוגה כפולה",
      "מיטה נוגה כפולה",
      "מיטת נוגה כפולה",
      "קומותיים נוגה כפולה",
      "נוגה",
      "דגם נוגה",
      "מיטה נוגה",
      "מיטת נוגה",
      "קומותיים נוגה",
      "נגה כפולה",
      "דגם נגה כפולה",
      "מיטה נגה כפולה",
      "מיטת נגה כפולה",
      "קומותיים נגה כפולה",
      "נגה",
      "דגם נגה",
      "מיטה נגה",
      "מיטת נגה",
      "קומותיים נגה",
      "קטלוג קומותיים נגר 2026"
    ],
    "3": [
      "נילי כפולה גב ריפוד היי רייזר",
      "דגם נילי כפולה גב ריפוד היי רייזר",
      "מיטה נילי כפולה גב ריפוד היי רייזר",
      "מיטת נילי כפולה גב ריפוד היי רייזר",
      "קומותיים נילי כפולה גב ריפוד היי רייזר",
      "נילי",
      "דגם נילי",
      "מיטה נילי",
      "מיטת נילי",
      "קומותיים נילי",
      "נילי כפולה",
      "דגם נילי כפולה",
      "מיטה נילי כפולה",
      "מיטת נילי כפולה",
      "קומותיים נילי כפולה",
      "נילי כפולה גב ריפוד היי ריזר",
      "דגם נילי כפולה גב ריפוד היי ריזר",
      "מיטה נילי כפולה גב ריפוד היי ריזר",
      "מיטת נילי כפולה גב ריפוד היי ריזר",
      "קומותיים נילי כפולה גב ריפוד היי ריזר",
      "נילי רייזר",
      "דגם נילי רייזר",
      "מיטה נילי רייזר",
      "מיטת נילי רייזר",
      "קומותיים נילי רייזר",
      "נילי ריזר",
      "דגם נילי ריזר",
      "מיטה נילי ריזר",
      "מיטת נילי ריזר",
      "קומותיים נילי ריזר",
      "קטלוג קומותיים נגר 2026"
    ],
    "4": [
      "אלון",
      "דגם אלון",
      "מיטה אלון",
      "מיטת אלון",
      "קומותיים אלון",
      "קטלוג קומותיים נגר 2026"
    ],
    "5": [
      "שקדיה",
      "דגם שקדיה",
      "מיטה שקדיה",
      "מיטת שקדיה",
      "קומותיים שקדיה",
      "קטלוג קומותיים נגר 2026"
    ],
    "6": [
      "מיתר",
      "דגם מיתר",
      "מיטה מיתר",
      "מיטת מיתר",
      "קומותיים מיתר",
      "קטלוג קומותיים נגר 2026"
    ],
    "7": [
      "מיתר",
      "דגם מיתר",
      "מיטה מיתר",
      "מיטת מיתר",
      "קומותיים מיתר",
      "קטלוג קומותיים נגר 2026"
    ],
    "8": [
      "שאנל",
      "דגם שאנל",
      "מיטה שאנל",
      "מיטת שאנל",
      "קומותיים שאנל",
      "קטלוג קומותיים נגר 2026"
    ],
    "9": [
      "שאנל",
      "דגם שאנל",
      "מיטה שאנל",
      "מיטת שאנל",
      "קומותיים שאנל",
      "קטלוג קומותיים נגר 2026"
    ],
    "10": [
      "נתיב",
      "דגם נתיב",
      "מיטה נתיב",
      "מיטת נתיב",
      "קומותיים נתיב",
      "קטלוג קומותיים נגר 2026"
    ],
    "11": [
      "נתיב",
      "דגם נתיב",
      "מיטה נתיב",
      "מיטת נתיב",
      "קומותיים נתיב",
      "קטלוג קומותיים נגר 2026"
    ],
    "12": [
      "מעגלים",
      "דגם מעגלים",
      "מיטה מעגלים",
      "מיטת מעגלים",
      "קומותיים מעגלים",
      "קטלוג קומותיים נגר 2026"
    ],
    "13": [
      "מעגלים",
      "דגם מעגלים",
      "מיטה מעגלים",
      "מיטת מעגלים",
      "קומותיים מעגלים",
      "קטלוג קומותיים נגר 2026"
    ],
    "14": [
      "ורד",
      "דגם ורד",
      "מיטה ורד",
      "מיטת ורד",
      "קומותיים ורד",
      "קטלוג קומותיים נגר 2026"
    ],
    "15": [
      "ורד",
      "דגם ורד",
      "מיטה ורד",
      "מיטת ורד",
      "קומותיים ורד",
      "קטלוג קומותיים נגר 2026"
    ],
    "16": [
      "קשת",
      "דגם קשת",
      "מיטה קשת",
      "מיטת קשת",
      "קומותיים קשת",
      "קטלוג קומותיים נגר 2026"
    ],
    "17": [
      "קשת",
      "דגם קשת",
      "מיטה קשת",
      "מיטת קשת",
      "קומותיים קשת",
      "קטלוג קומותיים נגר 2026"
    ],
    "18": [
      "ריבועים",
      "דגם ריבועים",
      "מיטה ריבועים",
      "מיטת ריבועים",
      "קומותיים ריבועים",
      "רבועים",
      "דגם רבועים",
      "מיטה רבועים",
      "מיטת רבועים",
      "קומותיים רבועים",
      "קטלוג קומותיים נגר 2026"
    ],
    "19": [
      "ריבועים",
      "דגם ריבועים",
      "מיטה ריבועים",
      "מיטת ריבועים",
      "קומותיים ריבועים",
      "רבועים",
      "דגם רבועים",
      "מיטה רבועים",
      "מיטת רבועים",
      "קומותיים רבועים",
      "קטלוג קומותיים נגר 2026"
    ],
    "20": [
      "קוביה",
      "דגם קוביה",
      "מיטה קוביה",
      "מיטת קוביה",
      "קומותיים קוביה",
      "קובייה",
      "דגם קובייה",
      "מיטה קובייה",
      "מיטת קובייה",
      "קומותיים קובייה",
      "קטלוג קומותיים נגר 2026"
    ],
    "21": [
      "קוביה",
      "דגם קוביה",
      "מיטה קוביה",
      "מיטת קוביה",
      "קומותיים קוביה",
      "קובייה",
      "דגם קובייה",
      "מיטה קובייה",
      "מיטת קובייה",
      "קומותיים קובייה",
      "קטלוג קומותיים נגר 2026"
    ],
    "22": [
      "נסיכה",
      "דגם נסיכה",
      "מיטה נסיכה",
      "מיטת נסיכה",
      "קומותיים נסיכה",
      "קטלוג קומותיים נגר 2026"
    ],
    "23": [
      "נסיכה",
      "דגם נסיכה",
      "מיטה נסיכה",
      "מיטת נסיכה",
      "קומותיים נסיכה",
      "קטלוג קומותיים נגר 2026"
    ],
    "24": [
      "פסים",
      "דגם פסים",
      "מיטה פסים",
      "מיטת פסים",
      "קומותיים פסים",
      "קטלוג קומותיים נגר 2026"
    ],
    "25": [
      "פסים",
      "דגם פסים",
      "מיטה פסים",
      "מיטת פסים",
      "קומותיים פסים",
      "קטלוג קומותיים נגר 2026"
    ],
    "26": [
      "גבריאל",
      "דגם גבריאל",
      "מיטה גבריאל",
      "מיטת גבריאל",
      "קומותיים גבריאל",
      "קטלוג קומותיים נגר 2026"
    ],
    "27": [
      "גבריאל",
      "דגם גבריאל",
      "מיטה גבריאל",
      "מיטת גבריאל",
      "קומותיים גבריאל",
      "קטלוג קומותיים נגר 2026"
    ],
    "28": [
      "רקפת",
      "דגם רקפת",
      "מיטה רקפת",
      "מיטת רקפת",
      "קומותיים רקפת",
      "קטלוג קומותיים נגר 2026"
    ],
    "29": [
      "רקפת",
      "דגם רקפת",
      "מיטה רקפת",
      "מיטת רקפת",
      "קומותיים רקפת",
      "קטלוג קומותיים נגר 2026"
    ],
    "30": [
      "מנשה",
      "דגם מנשה",
      "מיטה מנשה",
      "מיטת מנשה",
      "קומותיים מנשה",
      "קטלוג קומותיים נגר 2026"
    ],
    "31": [
      "מנשה",
      "דגם מנשה",
      "מיטה מנשה",
      "מיטת מנשה",
      "קומותיים מנשה",
      "קטלוג קומותיים נגר 2026"
    ],
    "32": [
      "נועם",
      "דגם נועם",
      "מיטה נועם",
      "מיטת נועם",
      "קומותיים נועם",
      "קטלוג קומותיים נגר 2026"
    ],
    "33": [
      "נועם",
      "דגם נועם",
      "מיטה נועם",
      "מיטת נועם",
      "קומותיים נועם",
      "קטלוג קומותיים נגר 2026"
    ],
    "34": [
      "נוי",
      "דגם נוי",
      "מיטה נוי",
      "מיטת נוי",
      "קומותיים נוי",
      "קטלוג קומותיים נגר 2026"
    ],
    "35": [
      "נוי",
      "דגם נוי",
      "מיטה נוי",
      "מיטת נוי",
      "קומותיים נוי",
      "קטלוג קומותיים נגר 2026"
    ],
    "36": [
      "כלנית",
      "דגם כלנית",
      "מיטה כלנית",
      "מיטת כלנית",
      "קומותיים כלנית",
      "קטלוג קומותיים נגר 2026"
    ],
    "37": [
      "כלנית",
      "דגם כלנית",
      "מיטה כלנית",
      "מיטת כלנית",
      "קומותיים כלנית",
      "קטלוג קומותיים נגר 2026"
    ],
    "38": [
      "רחל",
      "דגם רחל",
      "מיטה רחל",
      "מיטת רחל",
      "קומותיים רחל",
      "קטלוג קומותיים נגר 2026"
    ],
    "39": [
      "רחל",
      "דגם רחל",
      "מיטה רחל",
      "מיטת רחל",
      "קומותיים רחל",
      "קטלוג קומותיים נגר 2026"
    ],
    "40": [
      "ישי",
      "דגם ישי",
      "מיטה ישי",
      "מיטת ישי",
      "קומותיים ישי",
      "קטלוג קומותיים נגר 2026"
    ],
    "41": [
      "ישי מחורץ",
      "דגם ישי מחורץ",
      "מיטה ישי מחורץ",
      "מיטת ישי מחורץ",
      "קומותיים ישי מחורץ",
      "ישי",
      "דגם ישי",
      "מיטה ישי",
      "מיטת ישי",
      "קומותיים ישי",
      "קטלוג קומותיים נגר 2026"
    ],
    "42": [
      "ישי",
      "דגם ישי",
      "מיטה ישי",
      "מיטת ישי",
      "קומותיים ישי",
      "ישי מחורץ",
      "דגם ישי מחורץ",
      "מיטה ישי מחורץ",
      "מיטת ישי מחורץ",
      "קומותיים ישי מחורץ",
      "קטלוג קומותיים נגר 2026"
    ],
    "43": [
      "שלמה",
      "דגם שלמה",
      "מיטה שלמה",
      "מיטת שלמה",
      "קומותיים שלמה",
      "קטלוג קומותיים נגר 2026"
    ],
    "44": [
      "שלמה",
      "דגם שלמה",
      "מיטה שלמה",
      "מיטת שלמה",
      "קומותיים שלמה",
      "קטלוג קומותיים נגר 2026"
    ],
    "45": [
      "שביט",
      "דגם שביט",
      "מיטה שביט",
      "מיטת שביט",
      "קומותיים שביט",
      "קטלוג קומותיים נגר 2026"
    ],
    "46": [
      "שביט",
      "דגם שביט",
      "מיטה שביט",
      "מיטת שביט",
      "קומותיים שביט",
      "קטלוג קומותיים נגר 2026"
    ],
    "47": [
      "אורי",
      "דגם אורי",
      "מיטה אורי",
      "מיטת אורי",
      "קומותיים אורי",
      "קטלוג קומותיים נגר 2026"
    ],
    "48": [
      "אורי",
      "דגם אורי",
      "מיטה אורי",
      "מיטת אורי",
      "קומותיים אורי",
      "קטלוג קומותיים נגר 2026"
    ],
    "49": [
      "יאיר",
      "דגם יאיר",
      "מיטה יאיר",
      "מיטת יאיר",
      "קומותיים יאיר",
      "קטלוג קומותיים נגר 2026"
    ],
    "50": [
      "יאיר",
      "דגם יאיר",
      "מיטה יאיר",
      "מיטת יאיר",
      "קומותיים יאיר",
      "קטלוג קומותיים נגר 2026"
    ],
    "51": [
      "רפאל",
      "דגם רפאל",
      "מיטה רפאל",
      "מיטת רפאל",
      "קומותיים רפאל",
      "קטלוג קומותיים נגר 2026"
    ],
    "52": [
      "רפאל",
      "דגם רפאל",
      "מיטה רפאל",
      "מיטת רפאל",
      "קומותיים רפאל",
      "קטלוג קומותיים נגר 2026"
    ],
    "53": [
      "תמר",
      "דגם תמר",
      "מיטה תמר",
      "מיטת תמר",
      "קומותיים תמר",
      "קטלוג קומותיים נגר 2026"
    ],
    "54": [
      "תמר",
      "דגם תמר",
      "מיטה תמר",
      "מיטת תמר",
      "קומותיים תמר",
      "קטלוג קומותיים נגר 2026"
    ]
  }
}
